beakerx_base/__init__.py
beakerx_base/_version.py
beakerx_base/beakerx_widgets.py
beakerx_base/utils.py
beakerx_base/tests/__init__.py
beakerx_base/tests/test_utils.py
beakerx_base-2.3.0.dist-info/LICENSE
beakerx_base-2.3.0.dist-info/METADATA
beakerx_base-2.3.0.dist-info/NOTICE
beakerx_base-2.3.0.dist-info/WHEEL
beakerx_base-2.3.0.dist-info/top_level.txt
beakerx_base-2.3.0.dist-info/RECORD
